asciidoc/__init__.py
asciidoc/__main__.py
asciidoc/__metadata__.py
asciidoc/a2x.py
asciidoc/api.py
asciidoc/asciidoc.py
asciidoc/attrs.py
asciidoc/collections.py
asciidoc/exceptions.py
asciidoc/message.py
asciidoc/plugin.py
asciidoc/utils.py
asciidoc/blocks/__init__.py
asciidoc/blocks/table.py
asciidoc/resources/asciidoc.conf
asciidoc/resources/docbook45.conf
asciidoc/resources/docbook5.conf
asciidoc/resources/help.conf
asciidoc/resources/html4.conf
asciidoc/resources/html5.conf
asciidoc/resources/lang-ca.conf
asciidoc/resources/lang-cs.conf
asciidoc/resources/lang-de.conf
asciidoc/resources/lang-el.conf
asciidoc/resources/lang-en.conf
asciidoc/resources/lang-es.conf
asciidoc/resources/lang-fi.conf
asciidoc/resources/lang-fr.conf
asciidoc/resources/lang-hu.conf
asciidoc/resources/lang-id.conf
asciidoc/resources/lang-it.conf
asciidoc/resources/lang-ja.conf
asciidoc/resources/lang-nl.conf
asciidoc/resources/lang-pl.conf
asciidoc/resources/lang-pt-BR.conf
asciidoc/resources/lang-ro.conf
asciidoc/resources/lang-ru.conf
asciidoc/resources/lang-sv.conf
asciidoc/resources/lang-uk.conf
asciidoc/resources/lang-zh-CN.conf
asciidoc/resources/latex.conf
asciidoc/resources/slidy.conf
asciidoc/resources/text.conf
asciidoc/resources/xhtml11-quirks.conf
asciidoc/resources/xhtml11.conf
asciidoc/resources/dblatex/asciidoc-dblatex.sty
asciidoc/resources/dblatex/asciidoc-dblatex.xsl
asciidoc/resources/dblatex/dblatex-readme.txt
asciidoc/resources/docbook-xsl/asciidoc-docbook-xsl.txt
asciidoc/resources/docbook-xsl/chunked.xsl
asciidoc/resources/docbook-xsl/common.xsl
asciidoc/resources/docbook-xsl/epub.xsl
asciidoc/resources/docbook-xsl/fo.xsl
asciidoc/resources/docbook-xsl/htmlhelp.xsl
asciidoc/resources/docbook-xsl/manpage.xsl
asciidoc/resources/docbook-xsl/text.xsl
asciidoc/resources/docbook-xsl/xhtml.xsl
asciidoc/resources/filters/unwraplatex.py
asciidoc/resources/filters/code/code-filter-readme.txt
asciidoc/resources/filters/code/code-filter-test.txt
asciidoc-10.2.0.dist-info/LICENSE
asciidoc-10.2.0.dist-info/METADATA
asciidoc-10.2.0.dist-info/WHEEL
asciidoc-10.2.0.dist-info/entry_points.txt
asciidoc-10.2.0.dist-info/top_level.txt
asciidoc-10.2.0.dist-info/RECORD
